hyperas/__init__.py
hyperas/distributions.py
hyperas/ensemble.py
hyperas/optim.py
hyperas/utils.py
hyperas-0.4.1.dist-info/METADATA
hyperas-0.4.1.dist-info/RECORD
hyperas-0.4.1.dist-info/WHEEL
hyperas-0.4.1.dist-info/top_level.txt
