Metadata-Version: 1.1
Name: hyperas
Version: 0.4.1
Summary: Simple wrapper for hyperopt to do convenient hyperparameter optimization for Keras models
Home-page: http://github.com/maxpumperla/hyperas
Author: Max Pumperla
Author-email: max.pumperla@googlemail.com
License: MIT
Download-URL: https://github.com/maxpumperla/hyperas/tarball/0.4.1
Platform: UNKNOWN
